CHANGES.rst
CONTRIBUTORS.rst
MANIFEST.in
README.rst
VERSION
setup.cfg
setup.py
test.rst
docs/LICENSE.GPL
docs/LICENSE.rst
docs/index.html
docs/index.rst
src/visaplan/__init__.py
src/visaplan.plone.ajaxnavigation.egg-info/PKG-INFO
src/visaplan.plone.ajaxnavigation.egg-info/SOURCES.txt
src/visaplan.plone.ajaxnavigation.egg-info/dependency_links.txt
src/visaplan.plone.ajaxnavigation.egg-info/entry_points.txt
src/visaplan.plone.ajaxnavigation.egg-info/namespace_packages.txt
src/visaplan.plone.ajaxnavigation.egg-info/not-zip-safe
src/visaplan.plone.ajaxnavigation.egg-info/requires.txt
src/visaplan.plone.ajaxnavigation.egg-info/top_level.txt
src/visaplan/plone/__init__.py
src/visaplan/plone/ajaxnavigation/__init__.py
src/visaplan/plone/ajaxnavigation/config.py
src/visaplan/plone/ajaxnavigation/configure.zcml
src/visaplan/plone/ajaxnavigation/controlpanel.py
src/visaplan/plone/ajaxnavigation/data.py
src/visaplan/plone/ajaxnavigation/defaults.py
src/visaplan/plone/ajaxnavigation/interfaces.py
src/visaplan/plone/ajaxnavigation/oldcrumbs.py
src/visaplan/plone/ajaxnavigation/profiles.zcml
src/visaplan/plone/ajaxnavigation/setuphandlers.py
src/visaplan/plone/ajaxnavigation/testing.py
src/visaplan/plone/ajaxnavigation/utils.py
src/visaplan/plone/ajaxnavigation/locales/visaplan.plone.ajaxnavigation.pot
src/visaplan/plone/ajaxnavigation/locales/de/LC_MESSAGES/visaplan.plone.ajaxnavigation.po
src/visaplan/plone/ajaxnavigation/locales/en/LC_MESSAGES/visaplan.plone.ajaxnavigation.po
src/visaplan/plone/ajaxnavigation/profiles/default/browserlayer.xml
src/visaplan/plone/ajaxnavigation/profiles/default/controlpanel.xml
src/visaplan/plone/ajaxnavigation/profiles/default/cssregistry.xml
src/visaplan/plone/ajaxnavigation/profiles/default/jsregistry.xml
src/visaplan/plone/ajaxnavigation/profiles/default/metadata.xml
src/visaplan/plone/ajaxnavigation/profiles/default/registry/ajaxnavigation.xml
src/visaplan/plone/ajaxnavigation/profiles/uninstall/browserlayer.xml
src/visaplan/plone/ajaxnavigation/profiles/uninstall/controlpanel.xml
src/visaplan/plone/ajaxnavigation/profiles/uninstall/cssregistry.xml
src/visaplan/plone/ajaxnavigation/profiles/uninstall/jsregistry.xml
src/visaplan/plone/ajaxnavigation/profiles/uninstall/registry.xml
src/visaplan/plone/ajaxnavigation/resource/ajaxnavigation.js
src/visaplan/plone/ajaxnavigation/resource/ajaxnavigation.js.neu
src/visaplan/plone/ajaxnavigation/resource/ajaxnavigation.js.orig
