Metadata-Version: 2.1
Name: visaplan.plone.ajaxnavigation
Version: 1.0.0
Summary: Plone add-on to add AJAX navigation
Home-page: UNKNOWN
Author: Tobias Herp
Author-email: tobias.herp@visaplan.com
License: GPL version 2+
Project-URL: Source, https://github.com/visaplan/plone.ajaxnavigation
Project-URL: Documentation, https://pypi.org/project/visaplan.plone.ajaxnavigation
Project-URL: Tracker, https://github.com/visaplan/plone.ajaxnavigation/issues
Platform: UNKNOWN
Classifier: Environment :: Web Environment
Classifier: Framework :: Plone
Classifier: Framework :: Plone :: 4.3
Classifier: Programming Language :: Python
Classifier: Programming Language :: Python :: 2.7
Classifier: Programming Language :: Python :: 3
Classifier: Intended Audience :: Developers
Classifier: Natural Language :: German
Classifier: Operating System :: OS Independent
Classifier: License :: OSI Approved :: GNU General Public License v2 or later (GPLv2+)
Provides-Extra: test
